etym_cli/__init__.py
etym_cli/__main__.py
etym_cli/cli.py
etym_cli-0.0.3.dist-info/METADATA
etym_cli-0.0.3.dist-info/WHEEL
etym_cli-0.0.3.dist-info/entry_points.txt
etym_cli-0.0.3.dist-info/RECORD
