Metadata-Version: 2.4
Name: etym-cli
Version: 0.0.3
Summary: Command-line tool for etymonline with rich output.
Author: agmmnn
License: CC0
Requires-Python: >=3.12
Requires-Dist: beautifulsoup4
Requires-Dist: lxml
Requires-Dist: requests
Requires-Dist: rich
